archpy/__init__.py
archpy/__main__.py
archpy/lib/__init__.py
archpy/lib/booatloaders.py
archpy/lib/command.py
archpy/lib/config.py
archpy/lib/constants.py
archpy/lib/file.py
archpy/lib/installation.py
archpy/lib/packages.py
archpy/lib/partitions.py
archpy/lib/sysinfo.py
archpy/lib/text.py
archpy-1.0.1.dist-info/LICENSE
archpy-1.0.1.dist-info/METADATA
archpy-1.0.1.dist-info/WHEEL
archpy-1.0.1.dist-info/entry_points.txt
archpy-1.0.1.dist-info/top_level.txt
archpy-1.0.1.dist-info/RECORD
