Metadata-Version: 2.1
Name: archpy
Version: 1.0.1
Summary: Arch Linux install helper.
Home-page: UNKNOWN
Author: André Luís
Author-email: andreluisos@msn.com
License: GPL
Project-URL: Source, https://github.com/andreluisos/archpy
Project-URL: Documentation, https://github.com/andreluisos/archpy
Platform: UNKNOWN
Requires-Python: >=3.8
License-File: LICENSE
Requires-Dist: inquirer (~=2.7.0)
Requires-Dist: Unidecode (~=1.3.2)
